st_dataframe_paginator/README.md
st_dataframe_paginator/__init__.py
st_dataframe_paginator/example.py
st_dataframe_paginator/frontend/dist/index.html
st_dataframe_paginator/frontend/dist/assets/index-BwZ67_Ci.css
st_dataframe_paginator/frontend/dist/assets/index-BxH-SksS.js
st_dataframe_paginator-0.0.9.dist-info/licenses/LICENSE
st_dataframe_paginator-0.0.9.dist-info/METADATA
st_dataframe_paginator-0.0.9.dist-info/WHEEL
st_dataframe_paginator-0.0.9.dist-info/top_level.txt
st_dataframe_paginator-0.0.9.dist-info/RECORD
